app/__init__.py
app/ysh.py
ysh-0.0.1.1.dist-info/LICENSE
ysh-0.0.1.1.dist-info/METADATA
ysh-0.0.1.1.dist-info/WHEEL
ysh-0.0.1.1.dist-info/entry_points.txt
ysh-0.0.1.1.dist-info/top_level.txt
ysh-0.0.1.1.dist-info/RECORD
