Metadata-Version: 2.1
Name: ysh
Version: 0.0.1.1
Summary: A basic shell interface that can execute Unix commands
Home-page: https://github.com/zenilist/tsh
Author: Avi
Keywords: python,terminal
Classifier: Programming Language :: Python :: 3
Classifier: License :: OSI Approved :: MIT License
Classifier: Operating System :: Unix
License-File: LICENSE
Requires-Dist: sshkeyboard
